[
    {
        "name": "Auxiliary Blocks模组汉化",
        "desc": "来自宝藏猎人3，VPGS开源",
        "authors": "DrIceTea",
        "mods": "auxiliaryblocks-1.18.2-0.4.1",
        "dynamic": false
    },
    {
        "target_class": {
            "name": "iskallia.auxiliaryblocks.block.item.CategorizedBlockItem",
            "method": "m_7373_"
        },
        "pairs": [
            {
                "key": "Category: ",
                "value": "类型："
            },
            {
                "key": "Base Block of ",
                "value": "基础方块类型："
            },
            {
                "key": "Hint: ",
                "value": "提示："
            },
            {
                "key": "Can be transformed into other",
                "value": "可以转化为其它方块，"
            },
            {
                "key": "blocks using ",
                "value": "使用"
            },
            {
                "key": "Stonecutter",
                "value": "切石机"
            },
            {
                "key": ".",
                "value": "进行转化。"
            },
            {
                "key": "Base Block: ",
                "value": "基础方块："
            }
        ]
    },
    {
        "target_class": {
            "name": "iskallia.auxiliaryblocks.category.block.AsphaltBlockCategory",
            "method": ""
        },
        "key": "Asphalt",
        "value": "沥青"
    },
    {
        "target_class": {
            "name": "iskallia.auxiliaryblocks.category.block.CrystalBlockCategory",
            "method": ""
        },
        "key": "Crystal",
        "value": "水晶"
    },
    {
        "target_class": {
            "name": "iskallia.auxiliaryblocks.category.block.GelatinBlockCategory",
            "method": ""
        },
        "key": "Gelatin",
        "value": "凝胶"
    },
    {
        "target_class": {
            "name": "iskallia.auxiliaryblocks.category.block.IndustrialBlockCategory",
            "method": ""
        },
        "key": "Industrial",
        "value": "工业"
    },
    {
        "target_class": {
            "name": "iskallia.auxiliaryblocks.category.block.LabBlockCategory",
            "method": ""
        },
        "key": "Laboratory",
        "value": "实验室"
    },
    {
        "target_class": {
            "name": "iskallia.auxiliaryblocks.category.block.MetalsBlockCategory",
            "method": ""
        },
        "key": "Metals",
        "value": "金属"
    },
    {
        "target_class": {
            "name": "iskallia.auxiliaryblocks.category.block.NaturalBlockCategory",
            "method": ""
        },
        "key": "Natural",
        "value": "自然"
    },
    {
        "target_class": {
            "name": "iskallia.auxiliaryblocks.category.block.PastelBlockCategory",
            "method": ""
        },
        "key": "Pastel",
        "value": "蜡笔"
    },
    {
        "target_class": {
            "name": "iskallia.auxiliaryblocks.category.block.PlasticBlockCategory",
            "method": ""
        },
        "key": "Plastic",
        "value": "塑料"
    },
    {
        "target_class": {
            "name": "iskallia.auxiliaryblocks.category.block.SheetMetalBlockCategory",
            "method": ""
        },
        "key": "Sheet Metal",
        "value": "金属板"
    },
    {
        "target_class": {
            "name": "iskallia.auxiliaryblocks.init.ModBlocks",
            "method": ""
        },
        "pairs": [
            {
                "key": "Iskall's Favorite Block",
                "value": "伊斯卡最喜欢的方块"
            },
            {
                "key": "Blue",
                "value": "蓝色"
            },
            {
                "key": "Chrome",
                "value": "铬银色"
            },
            {
                "key": "Cyan",
                "value": "青色"
            },
            {
                "key": "Dark Gray",
                "value": "深灰色"
            },
            {
                "key": "Dark Metallic",
                "value": "深金属色"
            },
            {
                "key": "Gray",
                "value": "灰色"
            },
            {
                "key": "Green",
                "value": "绿色"
            },
            {
                "key": "Light Gray",
                "value": "浅灰色"
            },
            {
                "key": "Light Metallic",
                "value": "浅金属色"
            },
            {
                "key": "Metallic",
                "value": "金属色"
            },
            {
                "key": "Red",
                "value": "红色"
            },
            {
                "key": "Yellow",
                "value": "黄色"
            },
            {
                "key": "Black",
                "value": "黑色"
            },
            {
                "key": "Indigo",
                "value": "靛蓝色"
            },
            {
                "key": "Orange",
                "value": "橙色"
            },
            {
                "key": "Violet",
                "value": "紫色"
            },
            {
                "key": "White",
                "value": "白色"
            }
        ]
    }
]